[
    {
        "id": "video_001",
        "cover": "./assets/images/video-cover-image/video1.avif",
        "views": "17.7万",
        "danmu_number": 92,
        "title": "【丝之歌手书】Harpy Hare（蕾丝中心向/三公主）",
        "duration": "02:15",
        "author": "FN柴北鹦Chabry",
        "publish_time": "2025-10-03"
    },
    {
        "id": "video_002",
        "cover": "./assets/images/video-cover-image/video2.avif",
        "views": "17.2万",
        "danmu_number": 146,
        "title": "「星爵的磁带」The Chain - Fleetwood Mac 佛利伍麦克 百万级装备试听【Hi-Res】",
        "duration": "08:11",
        "author": "JLRS日落fm",
        "publish_time": "2023-10-17"
    },
    {
        "id": "video_003",
        "cover": "./assets/images/video-cover-image/video3.avif",
        "views": "18.5万",
        "danmu_number": 168,
        "title": "86个HTML&CSS小项目",
        "duration": "11:12:44",
        "author": "爱搞事的木易",
        "publish_time": "2021-04-04"
    },
    {
        "id": "video_004",
        "cover": "./assets/images/video-cover-image/video4.avif",
        "views": "1.1万",
        "danmu_number": 57,
        "title": "【纪录片/中英字幕】《球王：迭戈·马拉多纳 Diego Maradona》【那不勒斯】（2019）",
        "duration": "02:04:00",
        "author": "Leo_Tung",
        "publish_time": "2020-12-02"
    },
    {
        "id": "video_005",
        "cover": "./assets/images/video-cover-image/video5.avif",
        "views": "4.9万",
        "danmu_number": 29,
        "title": "【AI学习】2025年学习机器学习的最佳组合和顺序",
        "duration": "16:25",
        "author": "KrillinAI",
        "publish_time": "2025-03-12"
    },
    {
        "id": "video_006",
        "cover": "./assets/images/video-cover-image/video6.avif",
        "views": "11.8万",
        "danmu_number": 218,
        "title": "Elon Musk·马斯克最新3小时访谈 @ JoeRogan播客 2024.11.5【中英精校】",
        "duration": "10:05",
        "author": "Web3天空之城",
        "publish_time": "2024-11-05"
    },
    {
        "id": "video_007",
        "cover": "./assets/images/video-cover-image/video7.avif",
        "views": "286.1万",
        "danmu_number": "2.4万",
        "title": "【Unity教程】零基础带你从小白到超神",
        "duration": "14:48:24",
        "author": "Gamer飞羽",
        "publish_time": "2021-12-02"
    },
    {
        "id": "video_008",
        "cover": "./assets/images/video-cover-image/video8.avif",
        "views": "1.6万",
        "danmu_number": 41,
        "title": "【多平台音乐】《本所七大不可思议》原声OST",
        "duration": "09:22",
        "author": "电子游戏音乐",
        "publish_time": "2023-04-06"
    },
    {
        "id": "video_009",
        "cover": "./assets/images/video-cover-image/video9.avif",
        "views": "13.0万",
        "danmu_number": 223,
        "title": "导演们谈自己最喜欢的电影——昆汀、斯科塞斯、林奇、斯派克·李、埃德加·赖特拉片单了！",
        "duration": "11:22",
        "author": "爱看电影的逍遥猪",
        "publish_time": "2022-06-14"
    },
    {
        "id": "video_010",
        "cover": "./assets/images/video-cover-image/video10.avif",
        "views": 7611,
        "danmu_number": 6,
        "title": "【TNABO】《月光男孩》电影配乐-by Nicholas Britell",
        "duration": "38:07",
        "author": "zxc9668",
        "publish_time": "2017-02-10"
    },
    {
        "id": "video_011",
        "cover": "./assets/images/video-cover-image/video11.avif",
        "views": "4306.4万",
        "danmu_number": "68.2万",
        "title": "黑马程序员匠心之作|C++教程从0到1入门编程,学习编程不再难",
        "duration": "52:29:32",
        "author": "黑马程序员",
        "publish_time": "2019-01-24"
    },
    {
        "id": "video_012",
        "cover": "./assets/images/video-cover-image/video12.avif",
        "views": "281.7万",
        "danmu_number": 2227,
        "title": "燃到泪目！路飞最炸裂的一拳！",
        "duration": "08:45",
        "author": "柳碎willow",
        "publish_time": "2022-04-24"
    },
    {
        "id": "video_013",
        "cover": "./assets/images/video-cover-image/video13.avif",
        "views": "292.8万",
        "danmu_number": "23.3万",
        "title": "完结丨乱序版丨自创背词法丨六小时一轮丨四级词汇",
        "duration": "14:23:36",
        "author": "语言观止",
        "publish_time": "2020-07-12"
    },
    {
        "id": "video_014",
        "cover": "./assets/images/video-cover-image/video14.avif",
        "views": "30.2万",
        "danmu_number": 1773,
        "title": "摇滚交响音乐会——崔健",
        "duration": "01:26:08",
        "author": "quantum2077",
        "publish_time": "2021-06-20"
    },
    {
        "id": "video_015",
        "cover": "./assets/images/video-cover-image/video15.avif",
        "views": "3.0万",
        "danmu_number": 10,
        "title": "顶级纪录片 | 【必看】揭秘伯克希尔 巴芒金融帝国",
        "duration": "32:41",
        "author": "知识财富学院",
        "publish_time": "2023-10-25"
    },
    {
        "id": "video_016",
        "cover": "./assets/images/video-cover-image/video16.avif",
        "views": "1.9万",
        "danmu_number": 4,
        "title": "使用 U-NET 的 PyTorch 图像分割教程",
        "duration": "51:54",
        "author": "极市平台",
        "publish_time": "2023-06-28"
    }
]